{"MIL@STL":{"MIL":[{"name":"Jake Bauers","form_pct":52,"form_arrow":"up","pb":8.3,"hh":55.2,"la":19,"zone":0.5,"test":97.87},{"name":"Gary Sánchez","form_pct":67,"form_arrow":"up","pb":8.8,"hh":52.7,"la":17.3,"zone":0.5,"test":91.127},{"name":"Andrew Vaughn","form_pct":44,"form_arrow":"down","pb":5.1,"hh":51.1,"la":17.7,"zone":0.5,"test":67.962},{"name":"Brice Turang","form_pct":48,"form_arrow":"up","pb":2.7,"hh":40.5,"la":18.7,"zone":0.5,"test":43.648},{"name":"Sal Frelick","form_pct":71,"form_arrow":"up","pb":1.6,"hh":29.6,"la":17.1,"zone":0.5,"test":30.993},{"name":"Jackson Chourio","form_pct":47,"form_arrow":"up","pb":5.1,"hh":48.4,"la":16.1,"zone":0.5,"test":57.381},{"name":"William Contreras","form_pct":32,"form_arrow":"down","pb":4.8,"hh":52.1,"la":11.7,"zone":0.5,"test":51.42},{"name":"Garrett Mitchell","form_pct":58,"form_arrow":"up","pb":6.6,"hh":46.4,"la":13.6,"zone":0.5,"test":61.42},{"name":"Christian Yelich","form_pct":55,"form_arrow":"up","pb":4.1,"hh":51.2,"la":9.5,"zone":0.5,"test":45.38},{"name":"Joey Ortiz","form_pct":42,"form_arrow":"down","pb":2.2,"hh":40.3,"la":16.5,"zone":0.5,"test":26.657},{"name":"David Hamilton","form_pct":38,"form_arrow":"down","pb":3.4,"hh":33.9,"la":17.5,"zone":0.5,"test":34.192},{"name":"Blake Perkins","form_pct":49,"form_arrow":"down","pb":2.6,"hh":36.6,"la":16.9,"zone":0.5,"test":30.455},{"name":"Cooper Pratt","form_pct":37,"form_arrow":"down","pb":0,"hh":34.7,"la":11.4,"zone":0.5,"test":5.822}],"STL":[{"name":"Lars Nootbaar","form_pct":52,"form_arrow":"up","pb":7.1,"hh":52.1,"la":16.9,"zone":0.11,"test":86.553},{"name":"Bryan Torres","form_pct":54,"form_arrow":"up","pb":9.5,"hh":40,"la":22,"zone":0.06,"test":87.197},{"name":"Alec Burleson","form_pct":51,"form_arrow":"up","pb":5,"hh":52.7,"la":16.7,"zone":0.106,"test":69.172},{"name":"JJ Wetherholt","form_pct":53,"form_arrow":"up","pb":4.4,"hh":46.5,"la":19,"zone":0.1,"test":51.421},{"name":"Iván Herrera","form_pct":51,"form_arrow":"down","pb":4.5,"hh":50.4,"la":11.6,"zone":0.114,"test":54.286},{"name":"Blaze Jordan","form_pct":57,"form_arrow":"up","pb":4.6,"hh":52.9,"la":11.1,"zone":0.056,"test":56.266},{"name":"Nathan Church","form_pct":64,"form_arrow":"up","pb":5.4,"hh":41.8,"la":21.8,"zone":0.066,"test":53.849},{"name":"José Fermín","form_pct":53,"form_arrow":"down","pb":1.9,"hh":36.5,"la":16.1,"zone":0.076,"test":24.946},{"name":"Nelson Velázquez","form_pct":63,"form_arrow":"up","pb":8.1,"hh":42.8,"la":14.2,"zone":0.068,"test":67.591},{"name":"Pedro Pagés","form_pct":42,"form_arrow":"down","pb":4.9,"hh":40.2,"la":18,"zone":0.053,"test":42.438},{"name":"Masyn Winn","form_pct":50,"form_arrow":"down","pb":2.4,"hh":35.6,"la":19.2,"zone":0.069,"test":25.425},{"name":"Jordan Walker","form_pct":41,"form_arrow":"up","pb":7,"hh":52.3,"la":13.4,"zone":0.082,"test":57.946},{"name":"Jimmy Crooks","form_pct":42,"form_arrow":"down","pb":0,"hh":46.5,"la":15.9,"zone":0.039,"test":12.025}]},"CHC@BAL":{"CHC":[{"name":"Michael Busch","form_pct":37,"form_arrow":"down","pb":10,"hh":49.7,"la":18.6,"zone":0.098,"test":97.655},{"name":"Ian Happ","form_pct":55,"form_arrow":"down","pb":7.6,"hh":51.4,"la":20.3,"zone":0.091,"test":84.864},{"name":"Seiya Suzuki","form_pct":52,"form_arrow":"down","pb":7.3,"hh":50,"la":20.9,"zone":0.072,"test":82.018},{"name":"Pete Crow-Armstrong","form_pct":47,"form_arrow":"flat","pb":8.5,"hh":56.1,"la":21.9,"zone":0.125,"test":88.774},{"name":"Michael Conforto","form_pct":51,"form_arrow":"up","pb":6.5,"hh":51.7,"la":17.8,"zone":0.072,"test":73.813},{"name":"Alex Bregman","form_pct":40,"form_arrow":"up","pb":4.8,"hh":46.6,"la":21.8,"zone":0.086,"test":63.416},{"name":"Dansby Swanson","form_pct":72,"form_arrow":"up","pb":5.6,"hh":47,"la":15.5,"zone":0.091,"test":64.266},{"name":"Miguel Amaya","form_pct":45,"form_arrow":"down","pb":4.6,"hh":41.3,"la":20.3,"zone":0.09,"test":57.398},{"name":"Carson Kelly","form_pct":29,"form_arrow":"down","pb":3.8,"hh":42,"la":18.1,"zone":0.089,"test":51.291},{"name":"Nico Hoerner","form_pct":56,"form_arrow":"up","pb":1,"hh":32.1,"la":16.8,"zone":0.088,"test":33.798},{"name":"Pedro Ramírez","form_pct":47,"form_arrow":"down","pb":2.2,"hh":46,"la":12.8,"zone":0.09,"test":41.787},{"name":"Kevin Alcántara","form_pct":52,"form_arrow":"up","pb":0,"hh":40.5,"la":0.6,"zone":0.036,"test":13.769},{"name":"Justin Dean","form_pct":50,"form_arrow":"flat","pb":0,"hh":11.1,"la":18.4,"zone":0.052,"test":8.603}],"BAL":[{"name":"Tyler O'Neill","form_pct":74,"form_arrow":"up","pb":14,"hh":58.5,"la":21.9,"zone":0.058,"test":99.125},{"name":"Taylor Ward","form_pct":61,"form_arrow":"up","pb":7.6,"hh":47.9,"la":18.7,"zone":0.069,"test":69.831},{"name":"Pete Alonso","form_pct":41,"form_arrow":"up","pb":9.7,"hh":56.2,"la":21.7,"zone":0.081,"test":81.626},{"name":"Adley Rutschman","form_pct":28,"form_arrow":"up","pb":4.3,"hh":43.5,"la":17,"zone":0.073,"test":53.141},{"name":"Coby Mayo","form_pct":51,"form_arrow":"up","pb":8,"hh":55.8,"la":20.7,"zone":0.044,"test":65.093},{"name":"Blaze Alexander","form_pct":53,"form_arrow":"flat","pb":4.9,"hh":45.9,"la":17.2,"zone":0.055,"test":47.779},{"name":"Colton Cowser","form_pct":62,"form_arrow":"up","pb":7,"hh":45.2,"la":14.7,"zone":0.037,"test":54.152},{"name":"Gunnar Henderson","form_pct":49,"form_arrow":"up","pb":4.9,"hh":40.8,"la":14.1,"zone":0.114,"test":38.569},{"name":"Dylan Beavers","form_pct":59,"form_arrow":"up","pb":2.5,"hh":20.3,"la":24.6,"zone":0.066,"test":23.945},{"name":"Leody Taveras","form_pct":44,"form_arrow":"down","pb":2.3,"hh":34.1,"la":15.1,"zone":0.048,"test":22.359},{"name":"Jackson Holliday","form_pct":39,"form_arrow":"up","pb":3.9,"hh":36.6,"la":12.6,"zone":0.047,"test":29.127},{"name":"Jeremiah Jackson","form_pct":46,"form_arrow":"down","pb":6.6,"hh":57.2,"la":17.8,"zone":0.125,"test":39.765},{"name":"Samuel Basallo","form_pct":49,"form_arrow":"up","pb":1.4,"hh":44.4,"la":9.5,"zone":0.036,"test":9.359}]},"ATH@DET":{"ATH":[{"name":"Shea Langeliers","form_pct":35,"form_arrow":"flat","pb":8.3,"hh":54.5,"la":19.9,"zone":0.081,"test":91.203},{"name":"Jonah Heim","form_pct":53,"form_arrow":"down","pb":5.6,"hh":47.6,"la":18.1,"zone":0.102,"test":66.832},{"name":"Colby Thomas","form_pct":65,"form_arrow":"up","pb":10.8,"hh":49.1,"la":27.2,"zone":0.104,"test":85.564},{"name":"Henry Bolte","form_pct":59,"form_arrow":"up","pb":6.1,"hh":60.6,"la":10.3,"zone":0.06,"test":72.029},{"name":"Nick Kurtz","form_pct":55,"form_arrow":"flat","pb":5.2,"hh":52.2,"la":18,"zone":0.077,"test":68.374},{"name":"Joshua Kuroda-Grauer","form_pct":51,"form_arrow":"flat","pb":0,"hh":23.5,"la":21.8,"zone":0.014,"test":30.918},{"name":"Max Muncy","form_pct":42,"form_arrow":"down","pb":6.3,"hh":61.1,"la":21.4,"zone":0.049,"test":64.153},{"name":"Jeff McNeil","form_pct":61,"form_arrow":"up","pb":1.5,"hh":26.8,"la":15.8,"zone":0.083,"test":32.924},{"name":"Lawrence Butler","form_pct":58,"form_arrow":"up","pb":4.2,"hh":48.8,"la":11.9,"zone":0.079,"test":45.268},{"name":"Alika Williams","form_pct":51,"form_arrow":"down","pb":1.2,"hh":26.8,"la":17.4,"zone":0.082,"test":29.895},{"name":"Zack Gelof","form_pct":60,"form_arrow":"flat","pb":4.4,"hh":42.6,"la":19.1,"zone":0.067,"test":44.107},{"name":"Brian Serven","form_pct":50,"form_arrow":"flat","pb":0,"hh":36.3,"la":23.9,"zone":0.027,"test":13.456},{"name":"Carlos Cortes","form_pct":52,"form_arrow":"up","pb":0,"hh":25.6,"la":21.7,"zone":0.059,"test":7.284}],"DET":[{"name":"Kevin McGonigle","form_pct":57,"form_arrow":"up","pb":7.6,"hh":49.6,"la":22.3,"zone":0.06,"test":85.902},{"name":"Riley Greene","form_pct":74,"form_arrow":"flat","pb":9.3,"hh":57,"la":17.8,"zone":0.07,"test":93.677},{"name":"Spencer Torkelson","form_pct":56,"form_arrow":"up","pb":8.9,"hh":57.3,"la":20.9,"zone":0.038,"test":88.075},{"name":"Kerry Carpenter","form_pct":67,"form_arrow":"up","pb":9.2,"hh":55.4,"la":20.7,"zone":0.072,"test":87.462},{"name":"Colt Keith","form_pct":61,"form_arrow":"up","pb":5.7,"hh":48,"la":18.2,"zone":0.055,"test":65.208},{"name":"Dillon Dingler","form_pct":51,"form_arrow":"up","pb":6.2,"hh":52.8,"la":14.6,"zone":0.087,"test":69.575},{"name":"Matt Vierling","form_pct":53,"form_arrow":"flat","pb":3.7,"hh":43.9,"la":19.9,"zone":0.059,"test":50.961},{"name":"Zach McKinstry","form_pct":62,"form_arrow":"flat","pb":3.7,"hh":34.7,"la":21,"zone":0.086,"test":49.675},{"name":"James Outman","form_pct":50,"form_arrow":"down","pb":7.8,"hh":50.4,"la":20.4,"zone":0.044,"test":75.168},{"name":"Jake Rogers","form_pct":60,"form_arrow":"up","pb":4.8,"hh":42.2,"la":20.3,"zone":0.042,"test":57.392},{"name":"Jahmai Jones","form_pct":38,"form_arrow":"down","pb":4.1,"hh":37.5,"la":14,"zone":0.096,"test":36.264},{"name":"Hao-Yu Lee","form_pct":51,"form_arrow":"up","pb":5.5,"hh":29.8,"la":14.3,"zone":0.028,"test":38.112},{"name":"Ben Malgeri","form_pct":50,"form_arrow":"flat","pb":0,"hh":36.5,"la":22.2,"zone":0.008,"test":8.768}]},"ATL@PIT":{"ATL":[{"name":"Matt Olson","form_pct":52,"form_arrow":"up","pb":9.1,"hh":65.9,"la":22.9,"zone":0.11,"test":98.66},{"name":"Drake Baldwin","form_pct":21,"form_arrow":"up","pb":8.6,"hh":56.2,"la":17.5,"zone":0.111,"test":88.204},{"name":"Mike Yastrzemski","form_pct":39,"form_arrow":"down","pb":6.9,"hh":53.1,"la":22.5,"zone":0.101,"test":76.558},{"name":"Austin Riley","form_pct":32,"form_arrow":"down","pb":8.7,"hh":54.6,"la":17.8,"zone":0.059,"test":75.826},{"name":"Michael Harris","form_pct":36,"form_arrow":"down","pb":6.7,"hh":56.1,"la":14.2,"zone":0.093,"test":65.535},{"name":"Jim Jarvis","form_pct":50,"form_arrow":"flat","pb":0,"hh":44.5,"la":13.5,"zone":0.007,"test":24.203},{"name":"Dominic Smith","form_pct":31,"form_arrow":"down","pb":4.6,"hh":42.7,"la":17.6,"zone":0.105,"test":52.678},{"name":"Joey Bart","form_pct":65,"form_arrow":"down","pb":5,"hh":43,"la":12.1,"zone":0.077,"test":51.929},{"name":"Kyle Farmer","form_pct":46,"form_arrow":"down","pb":2.7,"hh":34.2,"la":15.9,"zone":0.065,"test":37.445},{"name":"Ozzie Albies","form_pct":72,"form_arrow":"up","pb":4.4,"hh":39.2,"la":20.3,"zone":0.158,"test":45.728},{"name":"Mauricio Dubón","form_pct":63,"form_arrow":"up","pb":2.1,"hh":31.4,"la":19.6,"zone":0.05,"test":33.194},{"name":"José Azócar","form_pct":49,"form_arrow":"down","pb":2.8,"hh":25.1,"la":11.8,"zone":0.042,"test":23.972},{"name":"Jorge Mateo","form_pct":62,"form_arrow":"up","pb":4,"hh":39.2,"la":19.9,"zone":0.043,"test":28.684}],"PIT":[{"name":"Esmerlyn Valdez","form_pct":57,"form_arrow":"down","pb":15.5,"hh":62.2,"la":16.4,"zone":0.048,"test":99.379},{"name":"Endy Rodríguez","form_pct":59,"form_arrow":"up","pb":4.3,"hh":52.9,"la":22.2,"zone":0.14,"test":58.714},{"name":"Ryan O'Hearn","form_pct":54,"form_arrow":"flat","pb":5.1,"hh":53.3,"la":16.7,"zone":0.074,"test":51.08},{"name":"Marcell Ozuna","form_pct":48,"form_arrow":"up","pb":8,"hh":51.6,"la":18.2,"zone":0.058,"test":58.994},{"name":"Henry Davis","form_pct":57,"form_arrow":"down","pb":5.9,"hh":55.9,"la":21.6,"zone":0.087,"test":48.727},{"name":"Bryan Reynolds","form_pct":60,"form_arrow":"up","pb":6.6,"hh":50,"la":14.3,"zone":0.071,"test":47.321},{"name":"Jared Triolo","form_pct":51,"form_arrow":"up","pb":3.3,"hh":45.5,"la":14.8,"zone":0.059,"test":29.904},{"name":"Brandon Lowe","form_pct":45,"form_arrow":"down","pb":10.3,"hh":54.4,"la":18.6,"zone":0.083,"test":53.42},{"name":"Tyler Callihan","form_pct":46,"form_arrow":"down","pb":12.3,"hh":58.9,"la":21.2,"zone":0.051,"test":59.646},{"name":"Jake Mangum","form_pct":62,"form_arrow":"up","pb":1.4,"hh":35.1,"la":13.2,"zone":0.176,"test":15.334},{"name":"Nick Gonzales","form_pct":45,"form_arrow":"up","pb":2.4,"hh":40.2,"la":12.7,"zone":0.07,"test":20.038},{"name":"Konnor Griffin","form_pct":66,"form_arrow":"up","pb":4.2,"hh":45.3,"la":10.4,"zone":0.087,"test":18.959},{"name":"Billy Cook","form_pct":43,"form_arrow":"flat","pb":3.4,"hh":33.9,"la":25.1,"zone":0.07,"test":20.544}]},"SEA@MIA":{"SEA":[{"name":"Cal Raleigh","form_pct":47,"form_arrow":"down","pb":11.7,"hh":63.3,"la":24.5,"zone":0.082,"test":98.483},{"name":"J.P. Crawford","form_pct":43,"form_arrow":"up","pb":3.7,"hh":43.7,"la":18.2,"zone":0.098,"test":47.373},{"name":"Cole Young","form_pct":40,"form_arrow":"down","pb":5.1,"hh":43.3,"la":23.7,"zone":0.102,"test":50.996},{"name":"Dominic Canzone","form_pct":51,"form_arrow":"down","pb":9.1,"hh":55.2,"la":14.8,"zone":0.076,"test":70.63},{"name":"Josh Naylor","form_pct":44,"form_arrow":"down","pb":5.7,"hh":49.7,"la":15.7,"zone":0.103,"test":47.342},{"name":"Mitch Garver","form_pct":40,"form_arrow":"down","pb":7.4,"hh":46.6,"la":22,"zone":0.046,"test":53.101},{"name":"Miles Mastrobuoni","form_pct":48,"form_arrow":"down","pb":1.6,"hh":34.7,"la":14.5,"zone":0.069,"test":23.935},{"name":"Randy Arozarena","form_pct":48,"form_arrow":"up","pb":5.2,"hh":50.6,"la":14.2,"zone":0.1,"test":41.07},{"name":"Buddy Kennedy","form_pct":50,"form_arrow":"flat","pb":2.7,"hh":37.4,"la":21.3,"zone":0.024,"test":26.12},{"name":"Luke Raley","form_pct":50,"form_arrow":"flat","pb":8.9,"hh":54.4,"la":17.1,"zone":0.059,"test":51.291},{"name":"Colt Emerson","form_pct":45,"form_arrow":"flat","pb":6.5,"hh":41.5,"la":20.7,"zone":0.093,"test":33.003},{"name":"Weston Wilson","form_pct":45,"form_arrow":"up","pb":2.3,"hh":48.8,"la":14.6,"zone":0.066,"test":18.255},{"name":"Victor Robles","form_pct":60,"form_arrow":"up","pb":2.5,"hh":31,"la":14.7,"zone":0.052,"test":10.54}],"MIA":[{"name":"Joe Mack","form_pct":51,"form_arrow":"down","pb":4.9,"hh":49,"la":15,"zone":0.5,"test":74.573},{"name":"Owen Caissie","form_pct":49,"form_arrow":"down","pb":9,"hh":49.2,"la":17.8,"zone":0.5,"test":91.964},{"name":"Liam Hicks","form_pct":41,"form_arrow":"flat","pb":3.4,"hh":34.5,"la":14.2,"zone":0.5,"test":43.641},{"name":"Jakob Marsee","form_pct":64,"form_arrow":"up","pb":4.1,"hh":44.1,"la":20.8,"zone":0.5,"test":50.49},{"name":"Kyle Stowers","form_pct":80,"form_arrow":"up","pb":10,"hh":60.1,"la":17.9,"zone":0.5,"test":83.457},{"name":"Xavier Edwards","form_pct":53,"form_arrow":"up","pb":1.4,"hh":28.6,"la":17.7,"zone":0.5,"test":29.439},{"name":"Javier Sanoja","form_pct":46,"form_arrow":"up","pb":1,"hh":40,"la":14.8,"zone":0.5,"test":26.025},{"name":"Otto Lopez","form_pct":34,"form_arrow":"up","pb":3.5,"hh":42.3,"la":12.7,"zone":0.5,"test":39.967},{"name":"Leo Jiménez","form_pct":60,"form_arrow":"up","pb":3.9,"hh":41,"la":16.2,"zone":0.5,"test":36.975},{"name":"Heriberto Hernández","form_pct":60,"form_arrow":"up","pb":5.9,"hh":50.1,"la":16.5,"zone":0.5,"test":51.298},{"name":"Griffin Conine","form_pct":49,"form_arrow":"up","pb":5.7,"hh":49.1,"la":13.9,"zone":0.5,"test":47.077},{"name":"Brian Navarreto","form_pct":48,"form_arrow":"down","pb":4.2,"hh":39.8,"la":8.7,"zone":0.5,"test":36.64},{"name":"Esteury Ruiz","form_pct":42,"form_arrow":"down","pb":3.3,"hh":27,"la":15,"zone":0.5,"test":16.661}]},"NYY@TB":{"NYY":[{"name":"Paul Goldschmidt","form_pct":26,"form_arrow":"down","pb":8.7,"hh":62.1,"la":20.4,"zone":0.051,"test":99.662},{"name":"Trent Grisham","form_pct":69,"form_arrow":"up","pb":7,"hh":41.6,"la":18.6,"zone":0.098,"test":58.998},{"name":"Ben Rice","form_pct":51,"form_arrow":"up","pb":8.7,"hh":49.1,"la":11.2,"zone":0.089,"test":72.489},{"name":"Cody Bellinger","form_pct":44,"form_arrow":"up","pb":5.1,"hh":39.9,"la":19.2,"zone":0.077,"test":44.024},{"name":"Max Schuemann","form_pct":63,"form_arrow":"flat","pb":6.3,"hh":34.8,"la":18.4,"zone":0.048,"test":45.699},{"name":"Anthony Volpe","form_pct":45,"form_arrow":"down","pb":5.1,"hh":47.7,"la":16.6,"zone":0.059,"test":40.581},{"name":"Amed Rosario","form_pct":55,"form_arrow":"up","pb":4.3,"hh":45.3,"la":15.9,"zone":0.052,"test":31.339},{"name":"José Caballero","form_pct":42,"form_arrow":"down","pb":5,"hh":37.3,"la":18.4,"zone":0.062,"test":36.549},{"name":"Ali Sánchez","form_pct":48,"form_arrow":"up","pb":2.2,"hh":37,"la":14.3,"zone":0.053,"test":18.754},{"name":"Austin Wells","form_pct":45,"form_arrow":"up","pb":3.3,"hh":48.5,"la":19.8,"zone":0.08,"test":16.736},{"name":"Jazz Chisholm","form_pct":55,"form_arrow":"up","pb":4.8,"hh":42.2,"la":12.3,"zone":0.068,"test":25.273},{"name":"Ryan McMahon","form_pct":48,"form_arrow":"up","pb":3.3,"hh":46,"la":15.8,"zone":0.072,"test":14.858},{"name":"Jasson Domínguez","form_pct":43,"form_arrow":"down","pb":3,"hh":56.1,"la":16.3,"zone":0.04,"test":16.714}],"TB":[{"name":"Jonathan Aranda","form_pct":54,"form_arrow":"down","pb":8.6,"hh":55.7,"la":20.6,"zone":0.112,"test":97.324},{"name":"Yandy Díaz","form_pct":56,"form_arrow":"up","pb":3,"hh":51.2,"la":14.2,"zone":0.079,"test":57.802},{"name":"Junior Caminero","form_pct":78,"form_arrow":"up","pb":8.6,"hh":58.2,"la":13.8,"zone":0.06,"test":84.503},{"name":"Victor Mesa","form_pct":59,"form_arrow":"flat","pb":7.5,"hh":52.4,"la":22.6,"zone":0.065,"test":73.452},{"name":"Cedric Mullins","form_pct":58,"form_arrow":"up","pb":5.2,"hh":48.5,"la":24.5,"zone":0.136,"test":59.261},{"name":"Nick Fortes","form_pct":60,"form_arrow":"up","pb":3.1,"hh":39.8,"la":16.9,"zone":0.067,"test":43.579},{"name":"Chandler Simpson","form_pct":50,"form_arrow":"up","pb":0,"hh":16.8,"la":8.1,"zone":0.074,"test":20.599},{"name":"Hunter Feduccia","form_pct":62,"form_arrow":"down","pb":3.3,"hh":42.5,"la":21.3,"zone":0.061,"test":50.835},{"name":"Taylor Walls","form_pct":71,"form_arrow":"flat","pb":3.4,"hh":32.3,"la":19.9,"zone":0.086,"test":41.076},{"name":"Richie Palacios","form_pct":44,"form_arrow":"down","pb":3.3,"hh":38,"la":17.8,"zone":0.087,"test":38.051},{"name":"Ryan Vilade","form_pct":71,"form_arrow":"up","pb":4.4,"hh":44.7,"la":19.3,"zone":0.06,"test":35.425},{"name":"Ben Williamson","form_pct":46,"form_arrow":"down","pb":0.4,"hh":41.5,"la":9.4,"zone":0.065,"test":11.239},{"name":"Jonny DeLuca","form_pct":56,"form_arrow":"down","pb":3.1,"hh":30.6,"la":15.7,"zone":0.051,"test":22.7}]},"HOU@WSH":{"HOU":[{"name":"Yordan Alvarez","form_pct":60,"form_arrow":"up","pb":9.5,"hh":59.1,"la":17.8,"zone":0.082,"test":91.372},{"name":"Isaac Paredes","form_pct":53,"form_arrow":"down","pb":5.1,"hh":47.2,"la":22.7,"zone":0.072,"test":64.647},{"name":"Jose Altuve","form_pct":45,"form_arrow":"down","pb":5.7,"hh":44.2,"la":16.2,"zone":0.047,"test":61.157},{"name":"Christian Walker","form_pct":45,"form_arrow":"down","pb":6.8,"hh":57.2,"la":21.9,"zone":0.039,"test":69.969},{"name":"Cam Smith","form_pct":63,"form_arrow":"up","pb":8,"hh":47.8,"la":20.2,"zone":0.068,"test":71.893},{"name":"Zach Dezenzo","form_pct":46,"form_arrow":"down","pb":8.2,"hh":41.1,"la":18.8,"zone":0.046,"test":83.414},{"name":"Christian Vázquez","form_pct":42,"form_arrow":"down","pb":3.6,"hh":38.6,"la":23.2,"zone":0.068,"test":48.451},{"name":"LaMonte Wade","form_pct":55,"form_arrow":"up","pb":1.2,"hh":34.1,"la":17.6,"zone":0.071,"test":39.302},{"name":"Nick Allen","form_pct":42,"form_arrow":"down","pb":1.3,"hh":29.1,"la":18.6,"zone":0.043,"test":31.691},{"name":"Brice Matthews","form_pct":39,"form_arrow":"down","pb":7.8,"hh":34.1,"la":20.4,"zone":0.021,"test":62.682},{"name":"Yainer Diaz","form_pct":47,"form_arrow":"down","pb":4.3,"hh":46,"la":15.9,"zone":0.046,"test":46.524},{"name":"Braden Shewmake","form_pct":43,"form_arrow":"up","pb":0,"hh":23.6,"la":10.2,"zone":0.053,"test":21.149},{"name":"Taylor Trammell","form_pct":64,"form_arrow":"up","pb":1.7,"hh":30.8,"la":9.6,"zone":0.02,"test":10.557}],"WSH":[{"name":"James Wood","form_pct":54,"form_arrow":"up","pb":8.1,"hh":66.5,"la":12.6,"zone":0.063,"test":98.97},{"name":"Keibert Ruiz","form_pct":56,"form_arrow":"up","pb":3.1,"hh":39.3,"la":18.3,"zone":0.059,"test":51.156},{"name":"Daylen Lile","form_pct":44,"form_arrow":"up","pb":6,"hh":45,"la":21.1,"zone":0.058,"test":63.406},{"name":"Luis García","form_pct":59,"form_arrow":"down","pb":5.8,"hh":46,"la":13.1,"zone":0.063,"test":60.287},{"name":"Curtis Mead","form_pct":46,"form_arrow":"down","pb":4.4,"hh":44.6,"la":17.2,"zone":0.042,"test":50.883},{"name":"CJ Abrams","form_pct":52,"form_arrow":"up","pb":5.6,"hh":46.8,"la":18.8,"zone":0.077,"test":55.145},{"name":"Jorbit Vivas","form_pct":49,"form_arrow":"down","pb":4.2,"hh":39.5,"la":16.4,"zone":0.062,"test":43.827},{"name":"Drew Millas","form_pct":62,"form_arrow":"up","pb":2.9,"hh":25.1,"la":12.4,"zone":0.061,"test":35.463},{"name":"Jacob Young","form_pct":34,"form_arrow":"down","pb":1.3,"hh":33.1,"la":9.7,"zone":0.05,"test":26.048},{"name":"Nasim Nuñez","form_pct":58,"form_arrow":"down","pb":0.4,"hh":22.8,"la":14.4,"zone":0.051,"test":14.484},{"name":"José Tena","form_pct":49,"form_arrow":"up","pb":5.2,"hh":52,"la":13.2,"zone":0.055,"test":43.253},{"name":"Andrés Chaparro","form_pct":52,"form_arrow":"up","pb":5.2,"hh":35.5,"la":23.4,"zone":0.027,"test":33.852},{"name":"Dylan Crews","form_pct":56,"form_arrow":"up","pb":4.7,"hh":44.4,"la":14.8,"zone":0.043,"test":33.298}]},"KC@NYM":{"KC":[{"name":"Bobby Witt","form_pct":62,"form_arrow":"up","pb":7.3,"hh":51.5,"la":22.8,"zone":0.5,"test":84.566},{"name":"Jac Caglianone","form_pct":59,"form_arrow":"flat","pb":8.7,"hh":64.4,"la":11.3,"zone":0.5,"test":93.972},{"name":"Nick Loftin","form_pct":46,"form_arrow":"down","pb":3.5,"hh":35.9,"la":13.3,"zone":0.5,"test":49.178},{"name":"Lane Thomas","form_pct":42,"form_arrow":"down","pb":5.5,"hh":44.5,"la":19.1,"zone":0.5,"test":59.174},{"name":"Carter Jensen","form_pct":74,"form_arrow":"up","pb":6.1,"hh":49.9,"la":21.9,"zone":0.5,"test":67.274},{"name":"Michael Massey","form_pct":36,"form_arrow":"down","pb":5.1,"hh":45.8,"la":20.2,"zone":0.5,"test":57.649},{"name":"Isaac Collins","form_pct":49,"form_arrow":"flat","pb":4.1,"hh":43.5,"la":19.2,"zone":0.5,"test":46.865},{"name":"Salvador Perez","form_pct":41,"form_arrow":"down","pb":8,"hh":53.9,"la":19.8,"zone":0.5,"test":79.41},{"name":"Josh Rojas","form_pct":51,"form_arrow":"up","pb":3.1,"hh":37.4,"la":17.8,"zone":0.5,"test":38.918},{"name":"Luke Maile","form_pct":50,"form_arrow":"flat","pb":5.4,"hh":32.5,"la":16.6,"zone":0.5,"test":50.815},{"name":"Starling Marte","form_pct":54,"form_arrow":"up","pb":4.4,"hh":43.3,"la":10.7,"zone":0.5,"test":42.549},{"name":"Kameron Misner","form_pct":43,"form_arrow":"down","pb":3.4,"hh":34.6,"la":17.7,"zone":0.5,"test":19.912},{"name":"Tyler Tolbert","form_pct":54,"form_arrow":"up","pb":2.5,"hh":41.9,"la":10.9,"zone":0.5,"test":8.392}],"NYM":[{"name":"Juan Soto","form_pct":34,"form_arrow":"flat","pb":9.5,"hh":61.7,"la":15.8,"zone":0.121,"test":96.368},{"name":"Francisco Lindor","form_pct":55,"form_arrow":"down","pb":7,"hh":56.6,"la":19.9,"zone":0.152,"test":56.78},{"name":"Jared Young","form_pct":50,"form_arrow":"down","pb":9.3,"hh":50.1,"la":16.7,"zone":0.094,"test":68.876},{"name":"Carson Benge","form_pct":57,"form_arrow":"down","pb":4.6,"hh":49.5,"la":16.3,"zone":0.091,"test":35.509},{"name":"A.J. Ewing","form_pct":59,"form_arrow":"up","pb":3.4,"hh":43.7,"la":19.4,"zone":0.146,"test":22.33},{"name":"Brett Baty","form_pct":56,"form_arrow":"up","pb":6.5,"hh":50.6,"la":14.3,"zone":0.117,"test":41.229},{"name":"Bo Bichette","form_pct":41,"form_arrow":"down","pb":4,"hh":54,"la":16,"zone":0.04,"test":24.346},{"name":"Luis Torrens","form_pct":38,"form_arrow":"down","pb":3.3,"hh":48.9,"la":12.1,"zone":0.05,"test":16.477},{"name":"Tyrone Taylor","form_pct":44,"form_arrow":"down","pb":4.7,"hh":40.5,"la":20.1,"zone":0.066,"test":22.069},{"name":"Eric Wagaman","form_pct":39,"form_arrow":"down","pb":4.1,"hh":49.1,"la":18,"zone":0.035,"test":17.267},{"name":"Francisco Alvarez","form_pct":41,"form_arrow":"down","pb":6.5,"hh":52.6,"la":14.7,"zone":0.041,"test":33.89},{"name":"Mark Vientos","form_pct":35,"form_arrow":"down","pb":7.7,"hh":50.7,"la":16.1,"zone":0.052,"test":43.779},{"name":"Ronny Mauricio","form_pct":49,"form_arrow":"down","pb":5.6,"hh":49.9,"la":16.7,"zone":0.13,"test":27.957}]},"PHI@CIN":{"PHI":[{"name":"Kyle Schwarber","form_pct":49,"form_arrow":"down","pb":10.2,"hh":64.1,"la":17.2,"zone":0.06,"test":99.033},{"name":"J.T. Realmuto","form_pct":47,"form_arrow":"down","pb":6.1,"hh":57.1,"la":17.8,"zone":0.128,"test":71.651},{"name":"Alec Bohm","form_pct":54,"form_arrow":"up","pb":5,"hh":49.7,"la":18.1,"zone":0.078,"test":60.314},{"name":"Derek Hill","form_pct":56,"form_arrow":"down","pb":6.7,"hh":48.9,"la":15,"zone":0.065,"test":66.862},{"name":"Trea Turner","form_pct":62,"form_arrow":"up","pb":5.5,"hh":48.4,"la":18.2,"zone":0.082,"test":60.355},{"name":"Bryce Harper","form_pct":57,"form_arrow":"up","pb":5.8,"hh":50.7,"la":14.9,"zone":0.075,"test":64.538},{"name":"Edmundo Sosa","form_pct":60,"form_arrow":"up","pb":5.8,"hh":49.5,"la":18.6,"zone":0.109,"test":60.179},{"name":"Bryson Stott","form_pct":43,"form_arrow":"up","pb":2,"hh":26.2,"la":16.3,"zone":0.057,"test":40.509},{"name":"Rafael Marchán","form_pct":58,"form_arrow":"up","pb":2,"hh":36.7,"la":13.6,"zone":0.092,"test":40.04},{"name":"Brandon Marsh","form_pct":42,"form_arrow":"down","pb":5,"hh":44.7,"la":15.3,"zone":0.065,"test":55.709},{"name":"Garrett Stubbs","form_pct":60,"form_arrow":"up","pb":0.7,"hh":33.1,"la":12.8,"zone":0.051,"test":34.478},{"name":"Justin Crawford","form_pct":59,"form_arrow":"down","pb":0,"hh":30.3,"la":1.8,"zone":0.096,"test":20.25},{"name":"Gabriel Rincones","form_pct":51,"form_arrow":"flat","pb":0,"hh":33.3,"la":-8.7,"zone":0,"test":0.941}],"CIN":[{"name":"Sal Stewart","form_pct":60,"form_arrow":"up","pb":5.4,"hh":46.9,"la":21.3,"zone":0.5,"test":81.381},{"name":"Eugenio Suárez","form_pct":47,"form_arrow":"down","pb":8.7,"hh":48.5,"la":18.3,"zone":0.5,"test":80.609},{"name":"Elly De La Cruz","form_pct":46,"form_arrow":"up","pb":6.2,"hh":51.6,"la":12.2,"zone":0.5,"test":66.336},{"name":"Nathaniel Lowe","form_pct":40,"form_arrow":"up","pb":4.2,"hh":49,"la":17.6,"zone":0.5,"test":53.198},{"name":"Tyler Stephenson","form_pct":46,"form_arrow":"down","pb":4.9,"hh":46.7,"la":17.5,"zone":0.5,"test":53.836},{"name":"Matt McLain","form_pct":42,"form_arrow":"down","pb":4.9,"hh":42.8,"la":21.9,"zone":0.5,"test":53.099},{"name":"Spencer Steer","form_pct":37,"form_arrow":"flat","pb":5.3,"hh":44,"la":20.3,"zone":0.5,"test":52.71},{"name":"JJ Bleday","form_pct":22,"form_arrow":"down","pb":6.1,"hh":44.3,"la":21.8,"zone":0.5,"test":56.09},{"name":"TJ Friedl","form_pct":30,"form_arrow":"down","pb":2.6,"hh":36.9,"la":17.5,"zone":0.5,"test":23.596},{"name":"Noelvi Marte","form_pct":64,"form_arrow":"up","pb":5.6,"hh":41.8,"la":13.2,"zone":0.5,"test":38.274},{"name":"Jose Trevino","form_pct":48,"form_arrow":"flat","pb":3.3,"hh":39.5,"la":15.9,"zone":0.5,"test":24.773},{"name":"Edwin Arroyo","form_pct":47,"form_arrow":"down","pb":0,"hh":34.6,"la":19.8,"zone":0.5,"test":18.641},{"name":"Ivan Johnson","form_pct":50,"form_arrow":"flat","pb":11.8,"hh":23.6,"la":13.7,"zone":0.5,"test":51.666}]},"CLE@MIN":{"CLE":[{"name":"Rhys Hoskins","form_pct":36,"form_arrow":"flat","pb":7.7,"hh":50.5,"la":21.3,"zone":0.076,"test":95.324},{"name":"Chase DeLauter","form_pct":49,"form_arrow":"down","pb":5.7,"hh":51.9,"la":19.8,"zone":0.048,"test":77.045},{"name":"Kyle Manzardo","form_pct":58,"form_arrow":"flat","pb":8.4,"hh":52.2,"la":24.1,"zone":0.079,"test":94.206},{"name":"Steven Kwan","form_pct":49,"form_arrow":"down","pb":1.6,"hh":23.1,"la":20.2,"zone":0.08,"test":42.78},{"name":"Daniel Schneemann","form_pct":62,"form_arrow":"up","pb":6.2,"hh":45.8,"la":17.3,"zone":0.072,"test":71.911},{"name":"Travis Bazzana","form_pct":67,"form_arrow":"up","pb":5.2,"hh":46.5,"la":16.5,"zone":0.086,"test":60.165},{"name":"David Fry","form_pct":42,"form_arrow":"down","pb":5.4,"hh":47.7,"la":21.5,"zone":0.057,"test":57.466},{"name":"Patrick Bailey","form_pct":34,"form_arrow":"down","pb":3.8,"hh":43.9,"la":16.2,"zone":0.064,"test":48.76},{"name":"Kahlil Watson","form_pct":46,"form_arrow":"down","pb":3.5,"hh":53.9,"la":6.6,"zone":0.074,"test":50.882},{"name":"Gabriel Arias","form_pct":62,"form_arrow":"up","pb":3.2,"hh":48.7,"la":11.2,"zone":0.06,"test":50.686},{"name":"Brayan Rocchio","form_pct":57,"form_arrow":"down","pb":1.6,"hh":35.8,"la":15.2,"zone":0.089,"test":28.948},{"name":"Austin Hedges","form_pct":49,"form_arrow":"down","pb":2.5,"hh":30.2,"la":21,"zone":0.055,"test":25.825},{"name":"Cooper Ingle","form_pct":50,"form_arrow":"flat","pb":0,"hh":60,"la":4.1,"zone":0.003,"test":6.496}],"MIN":[{"name":"Byron Buxton","form_pct":58,"form_arrow":"flat","pb":15.8,"hh":64.3,"la":20.7,"zone":0.067,"test":97.709},{"name":"Austin Martin","form_pct":36,"form_arrow":"down","pb":3.5,"hh":36.4,"la":17.7,"zone":0.054,"test":46.455},{"name":"Luke Keaschall","form_pct":51,"form_arrow":"up","pb":3.2,"hh":30.6,"la":18.8,"zone":0.057,"test":44.019},{"name":"Royce Lewis","form_pct":56,"form_arrow":"up","pb":7.6,"hh":44.3,"la":20.6,"zone":0.069,"test":59.519},{"name":"Kody Clemens","form_pct":54,"form_arrow":"up","pb":2.8,"hh":51.6,"la":17.3,"zone":0.034,"test":49.624},{"name":"Victor Caratini","form_pct":60,"form_arrow":"down","pb":6.4,"hh":43.6,"la":16.7,"zone":0.039,"test":52.843},{"name":"Josh Bell","form_pct":66,"form_arrow":"up","pb":5.1,"hh":40.2,"la":17.7,"zone":0.058,"test":46.767},{"name":"Tristan Gray","form_pct":37,"form_arrow":"up","pb":11.7,"hh":63.4,"la":14.2,"zone":0.027,"test":72.882},{"name":"Brooks Lee","form_pct":53,"form_arrow":"flat","pb":5.6,"hh":40.6,"la":13.9,"zone":0.074,"test":44.644},{"name":"Ryan Kreidler","form_pct":51,"form_arrow":"down","pb":4.7,"hh":37.5,"la":13.2,"zone":0.031,"test":39.307},{"name":"Trevor Larnach","form_pct":71,"form_arrow":"up","pb":2.9,"hh":48.3,"la":9.7,"zone":0.043,"test":31.588},{"name":"Alex Jackson","form_pct":49,"form_arrow":"down","pb":6.5,"hh":46.5,"la":23.9,"zone":0.058,"test":45.266},{"name":"Kyler Fedko","form_pct":43,"form_arrow":"down","pb":0,"hh":80,"la":10.7,"zone":0,"test":8.921}]},"BOS@CWS":{"BOS":[{"name":"Willson Contreras","form_pct":62,"form_arrow":"up","pb":8.7,"hh":55.8,"la":17.1,"zone":0.038,"test":94.3},{"name":"Romy Gonzalez","form_pct":50,"form_arrow":"flat","pb":9.6,"hh":59.7,"la":14.8,"zone":0.036,"test":90.003},{"name":"Andruw Monasterio","form_pct":55,"form_arrow":"up","pb":5.7,"hh":41.3,"la":20.6,"zone":0.06,"test":66.914},{"name":"Caleb Durbin","form_pct":52,"form_arrow":"down","pb":4.5,"hh":38.8,"la":18,"zone":0.056,"test":58.648},{"name":"Ceddanne Rafaela","form_pct":46,"form_arrow":"flat","pb":8.1,"hh":48.2,"la":18.4,"zone":0.034,"test":79.399},{"name":"Connor Wong","form_pct":63,"form_arrow":"up","pb":5.1,"hh":50.6,"la":22.5,"zone":0.042,"test":63.762},{"name":"Wilyer Abreu","form_pct":29,"form_arrow":"down","pb":3.5,"hh":43.8,"la":18.3,"zone":0.125,"test":56.212},{"name":"Carlos Narváez","form_pct":56,"form_arrow":"flat","pb":3.9,"hh":49.3,"la":20.4,"zone":0.074,"test":56.077},{"name":"Jarren Duran","form_pct":47,"form_arrow":"up","pb":1.9,"hh":43.9,"la":13.3,"zone":0.135,"test":47.454},{"name":"Nate Eaton","form_pct":49,"form_arrow":"down","pb":3.9,"hh":42.9,"la":18.1,"zone":0.028,"test":53.119},{"name":"Masataka Yoshida","form_pct":45,"form_arrow":"down","pb":1.9,"hh":35.8,"la":4.6,"zone":0.136,"test":35.023},{"name":"Anthony Seigler","form_pct":53,"form_arrow":"up","pb":0,"hh":28.6,"la":27.5,"zone":0.016,"test":25.584},{"name":"Tsung-Che Cheng","form_pct":50,"form_arrow":"flat","pb":0,"hh":41.5,"la":18.5,"zone":0.007,"test":7.191}],"CWS":[{"name":"Randal Grichuk","form_pct":44,"form_arrow":"flat","pb":8.3,"hh":61.5,"la":19.7,"zone":0.095,"test":90.21},{"name":"Jacob Gonzalez","form_pct":58,"form_arrow":"down","pb":0,"hh":51.3,"la":24.3,"zone":0.029,"test":55.976},{"name":"Miguel Vargas","form_pct":72,"form_arrow":"up","pb":6,"hh":45.3,"la":25,"zone":0.047,"test":70.792},{"name":"Sam Antonacci","form_pct":67,"form_arrow":"up","pb":0,"hh":28.6,"la":5.4,"zone":0.096,"test":37.122},{"name":"Chase Meidroth","form_pct":44,"form_arrow":"up","pb":1.8,"hh":47.6,"la":15.2,"zone":0.083,"test":43.741},{"name":"Colson Montgomery","form_pct":50,"form_arrow":"down","pb":9,"hh":47.7,"la":14.6,"zone":0.111,"test":75.613},{"name":"Junior Perez","form_pct":50,"form_arrow":"flat","pb":11,"hh":63.4,"la":9.8,"zone":0.038,"test":78.411},{"name":"Luisangel Acuña","form_pct":27,"form_arrow":"down","pb":3.2,"hh":40.8,"la":15.8,"zone":0.078,"test":39.881},{"name":"Andrew Benintendi","form_pct":32,"form_arrow":"down","pb":4.1,"hh":33.8,"la":20.3,"zone":0.115,"test":45.612},{"name":"Drew Romo","form_pct":56,"form_arrow":"flat","pb":4.7,"hh":47.6,"la":7.1,"zone":0.028,"test":50.566},{"name":"Kyle Teel","form_pct":51,"form_arrow":"up","pb":0,"hh":40.9,"la":4.5,"zone":0.101,"test":30.525},{"name":"Tristan Peters","form_pct":66,"form_arrow":"up","pb":0,"hh":7.4,"la":9.8,"zone":0.058,"test":12.79},{"name":"Braden Montgomery","form_pct":57,"form_arrow":"up","pb":0,"hh":41.7,"la":34,"zone":0.015,"test":8.774}]},"LAA@TEX":{"LAA":[{"name":"Jorge Soler","form_pct":58,"form_arrow":"up","pb":7.4,"hh":52.4,"la":16,"zone":0.046,"test":91.744},{"name":"Jo Adell","form_pct":49,"form_arrow":"flat","pb":7.2,"hh":54.5,"la":19.5,"zone":0.075,"test":90.65},{"name":"Zach Neto","form_pct":47,"form_arrow":"down","pb":7.9,"hh":50.6,"la":15.3,"zone":0.116,"test":86.55},{"name":"Nolan Schanuel","form_pct":69,"form_arrow":"flat","pb":2.8,"hh":35.7,"la":16.5,"zone":0.07,"test":47.174},{"name":"Josh Lowe","form_pct":66,"form_arrow":"up","pb":6,"hh":48.8,"la":20.5,"zone":0.13,"test":73.849},{"name":"Logan O'Hoppe","form_pct":40,"form_arrow":"down","pb":6.8,"hh":51.4,"la":16.6,"zone":0.043,"test":82.742},{"name":"Wade Meckler","form_pct":49,"form_arrow":"down","pb":4.3,"hh":30.6,"la":11.3,"zone":0.059,"test":47.64},{"name":"Denzer Guzman","form_pct":37,"form_arrow":"down","pb":5,"hh":48.5,"la":17.9,"zone":0.032,"test":58.403},{"name":"Donovan Walton","form_pct":59,"form_arrow":"up","pb":4.4,"hh":37.9,"la":17.9,"zone":0.087,"test":49.186},{"name":"Vaughn Grissom","form_pct":58,"form_arrow":"flat","pb":2.8,"hh":38.6,"la":14.2,"zone":0.074,"test":36.006},{"name":"Jose Siri","form_pct":58,"form_arrow":"down","pb":8.2,"hh":39,"la":16.5,"zone":0.084,"test":69.644},{"name":"Tyler Heineman","form_pct":50,"form_arrow":"down","pb":1.4,"hh":25.6,"la":21.3,"zone":0.1,"test":16.446},{"name":"Oswald Peraza","form_pct":41,"form_arrow":"down","pb":2.6,"hh":37.8,"la":10.2,"zone":0.083,"test":15.628}],"TEX":[{"name":"Joc Pederson","form_pct":66,"form_arrow":"up","pb":8.6,"hh":61.4,"la":21.2,"zone":0.157,"test":98.791},{"name":"Brandon Nimmo","form_pct":69,"form_arrow":"up","pb":6.8,"hh":58.3,"la":18.2,"zone":0.121,"test":85.459},{"name":"Josh Smith","form_pct":37,"form_arrow":"down","pb":3.6,"hh":43.3,"la":18.1,"zone":0.102,"test":59.082},{"name":"Alejandro Osuna","form_pct":60,"form_arrow":"up","pb":2.6,"hh":39.7,"la":17.5,"zone":0.166,"test":50.075},{"name":"Evan Carter","form_pct":35,"form_arrow":"down","pb":7,"hh":45,"la":18.3,"zone":0.095,"test":71.307},{"name":"Kyle Higashioka","form_pct":49,"form_arrow":"up","pb":5.1,"hh":49.9,"la":18.1,"zone":0.038,"test":68.498},{"name":"Justin Foscue","form_pct":54,"form_arrow":"up","pb":5.8,"hh":40.3,"la":21.5,"zone":0.061,"test":57.864},{"name":"Josh Jung","form_pct":35,"form_arrow":"up","pb":3.9,"hh":49.9,"la":15.3,"zone":0.065,"test":52.712},{"name":"Jake Burger","form_pct":58,"form_arrow":"flat","pb":7.1,"hh":55.7,"la":15.3,"zone":0.05,"test":65.858},{"name":"Nicky Lopez","form_pct":62,"form_arrow":"down","pb":0.6,"hh":25.1,"la":12,"zone":0.106,"test":20.596},{"name":"Cam Cauley","form_pct":51,"form_arrow":"up","pb":0,"hh":11.5,"la":19,"zone":0.006,"test":13.681},{"name":"Ezequiel Duran","form_pct":61,"form_arrow":"down","pb":3.6,"hh":42.3,"la":18.6,"zone":0.075,"test":40.153},{"name":"Elias Díaz","form_pct":58,"form_arrow":"up","pb":4,"hh":41.2,"la":17.8,"zone":0.091,"test":32.175}]},"AZ@SD":{"AZ":[{"name":"Ketel Marte","form_pct":57,"form_arrow":"down","pb":7.8,"hh":56.7,"la":14.4,"zone":0.5,"test":97.563},{"name":"Max Kepler","form_pct":50,"form_arrow":"flat","pb":6.8,"hh":50.8,"la":17.8,"zone":0.5,"test":77.812},{"name":"Corbin Carroll","form_pct":54,"form_arrow":"flat","pb":6.4,"hh":51.3,"la":17.3,"zone":0.5,"test":75.988},{"name":"Gabriel Moreno","form_pct":40,"form_arrow":"down","pb":3.9,"hh":47.9,"la":15.8,"zone":0.5,"test":55.991},{"name":"Tommy Troy","form_pct":51,"form_arrow":"down","pb":6.1,"hh":34.4,"la":15.6,"zone":0.5,"test":70.32},{"name":"Pavin Smith","form_pct":58,"form_arrow":"flat","pb":5.6,"hh":46.6,"la":14.8,"zone":0.5,"test":66.202},{"name":"Nolan Arenado","form_pct":48,"form_arrow":"up","pb":4.8,"hh":46.1,"la":20.3,"zone":0.5,"test":57.006},{"name":"Geraldo Perdomo","form_pct":49,"form_arrow":"up","pb":2.9,"hh":34.4,"la":17.4,"zone":0.5,"test":35.209},{"name":"Lourdes Gurriel","form_pct":66,"form_arrow":"up","pb":4.8,"hh":45.9,"la":17,"zone":0.5,"test":47.614},{"name":"Ildemaro Vargas","form_pct":58,"form_arrow":"up","pb":2.1,"hh":37.8,"la":9.2,"zone":0.5,"test":7.237},{"name":"Jorge Barrosa","form_pct":48,"form_arrow":"up","pb":4.2,"hh":36.4,"la":17.3,"zone":0.5,"test":26.296},{"name":"James McCann","form_pct":32,"form_arrow":"down","pb":5.2,"hh":46.6,"la":15.8,"zone":0.5,"test":39.43},{"name":"Tim Tawa","form_pct":52,"form_arrow":"down","pb":4.6,"hh":47,"la":12.9,"zone":0.5,"test":31.612}],"SD":[{"name":"Gavin Sheets","form_pct":42,"form_arrow":"down","pb":7,"hh":55.6,"la":20.3,"zone":0.045,"test":91.982},{"name":"Jackson Merrill","form_pct":46,"form_arrow":"up","pb":6.1,"hh":55.6,"la":21.2,"zone":0.084,"test":93.482},{"name":"Jake Cronenworth","form_pct":49,"form_arrow":"flat","pb":5.3,"hh":44.9,"la":20.7,"zone":0.042,"test":71.48},{"name":"Manny Machado","form_pct":57,"form_arrow":"down","pb":6.3,"hh":55.6,"la":20.8,"zone":0.044,"test":80.681},{"name":"Sung-Mun Song","form_pct":62,"form_arrow":"flat","pb":2.3,"hh":36.4,"la":16.4,"zone":0.039,"test":51.64},{"name":"Fernando Tatis","form_pct":61,"form_arrow":"up","pb":6.7,"hh":57,"la":11.9,"zone":0.062,"test":78.806},{"name":"Xander Bogaerts","form_pct":37,"form_arrow":"down","pb":4.4,"hh":42.4,"la":11.1,"zone":0.04,"test":45.674},{"name":"Ty France","form_pct":74,"form_arrow":"up","pb":3.5,"hh":44.5,"la":16.6,"zone":0.06,"test":44.45},{"name":"Rodolfo Durán","form_pct":47,"form_arrow":"up","pb":4.5,"hh":33.6,"la":15,"zone":0.13,"test":40.683},{"name":"Miguel Andujar","form_pct":40,"form_arrow":"up","pb":2.6,"hh":43.4,"la":12.9,"zone":0.046,"test":30.636},{"name":"Luis Campusano","form_pct":62,"form_arrow":"up","pb":3,"hh":44.1,"la":13.9,"zone":0.064,"test":32.226},{"name":"Samad Taylor","form_pct":57,"form_arrow":"up","pb":0.9,"hh":24.1,"la":10.6,"zone":0.063,"test":11.037},{"name":"Jase Bowen","form_pct":36,"form_arrow":"down","pb":0,"hh":32.2,"la":13.9,"zone":0.085,"test":23.573}]},"TOR@SF":{"TOR":[{"name":"Vladimir Guerrero","form_pct":47,"form_arrow":"up","pb":6.8,"hh":56,"la":12.7,"zone":0.046,"test":88.603},{"name":"Daulton Varsho","form_pct":49,"form_arrow":"up","pb":7.4,"hh":51.8,"la":23.2,"zone":0.112,"test":92.182},{"name":"Luis Urías","form_pct":48,"form_arrow":"down","pb":5,"hh":39.5,"la":18.8,"zone":0.088,"test":74.348},{"name":"Alejandro Kirk","form_pct":53,"form_arrow":"up","pb":3.2,"hh":51,"la":18.2,"zone":0.046,"test":67.091},{"name":"Yohendrick Piñango","form_pct":40,"form_arrow":"down","pb":5.3,"hh":52.1,"la":21.2,"zone":0.114,"test":78.848},{"name":"George Springer","form_pct":39,"form_arrow":"down","pb":7.1,"hh":47.8,"la":14.7,"zone":0.059,"test":87.241},{"name":"Myles Straw","form_pct":26,"form_arrow":"down","pb":0.7,"hh":23.8,"la":18.9,"zone":0.048,"test":42.715},{"name":"Kazuma Okamoto","form_pct":38,"form_arrow":"down","pb":7.3,"hh":58,"la":21.1,"zone":0.035,"test":91.146},{"name":"Nathan Lukes","form_pct":57,"form_arrow":"flat","pb":2.6,"hh":40.5,"la":20.2,"zone":0.228,"test":53.162},{"name":"Brandon Valenzuela","form_pct":54,"form_arrow":"up","pb":6.3,"hh":43.8,"la":22,"zone":0.113,"test":77.254},{"name":"Ernie Clement","form_pct":53,"form_arrow":"flat","pb":1.7,"hh":28.1,"la":18.2,"zone":0.05,"test":42.563},{"name":"Jonatan Clase","form_pct":50,"form_arrow":"flat","pb":5.3,"hh":37.8,"la":18.7,"zone":0.094,"test":61.137},{"name":"Andrés Giménez","form_pct":53,"form_arrow":"down","pb":3.8,"hh":36,"la":16.6,"zone":0.146,"test":49.074},{"name":"Sean Keys","form_pct":51,"form_arrow":"up","pb":0,"hh":83.3,"la":15.3,"zone":0.025,"test":9.767}],"SF":[{"name":"Rafael Devers","form_pct":57,"form_arrow":"down","pb":7.7,"hh":61.1,"la":20.4,"zone":0.5,"test":89.575},{"name":"Victor Bericoto","form_pct":44,"form_arrow":"up","pb":10.3,"hh":56.3,"la":11.7,"zone":0.5,"test":93.137},{"name":"Drew Cavanaugh","form_pct":52,"form_arrow":"up","pb":7.1,"hh":28.6,"la":18.5,"zone":0.5,"test":71.674},{"name":"Casey Schmitt","form_pct":67,"form_arrow":"up","pb":7,"hh":49.6,"la":20.9,"zone":0.5,"test":76.028},{"name":"Willy Adames","form_pct":15,"form_arrow":"down","pb":6.7,"hh":47.2,"la":19.6,"zone":0.5,"test":76.253},{"name":"Bryce Eldridge","form_pct":40,"form_arrow":"up","pb":4.3,"hh":61,"la":16.4,"zone":0.5,"test":69.17},{"name":"Heliot Ramos","form_pct":51,"form_arrow":"flat","pb":6,"hh":52.4,"la":18.1,"zone":0.5,"test":71.232},{"name":"Luis Arraez","form_pct":58,"form_arrow":"up","pb":1.2,"hh":25.2,"la":18.9,"zone":0.5,"test":28.992},{"name":"Jung Hoo Lee","form_pct":19,"form_arrow":"down","pb":2.9,"hh":37.8,"la":12.8,"zone":0.5,"test":36.777},{"name":"Eric Haase","form_pct":42,"form_arrow":"down","pb":6.5,"hh":42,"la":15.6,"zone":0.5,"test":57.406},{"name":"Drew Gilbert","form_pct":54,"form_arrow":"down","pb":2.4,"hh":37.1,"la":16.9,"zone":0.5,"test":27.894},{"name":"Christian Koss","form_pct":42,"form_arrow":"down","pb":3.5,"hh":32.5,"la":12.3,"zone":0.5,"test":26.776},{"name":"Jonah Cox","form_pct":54,"form_arrow":"up","pb":0,"hh":42.9,"la":29.3,"zone":0.5,"test":19.355}]},"COL@LAD":{"COL":[{"name":"Braxton Fulford","form_pct":36,"form_arrow":"down","pb":9.1,"hh":53.4,"la":33.2,"zone":0.044,"test":86.225},{"name":"Tyler Freeman","form_pct":42,"form_arrow":"up","pb":2.5,"hh":38.1,"la":17.4,"zone":0.096,"test":52.086},{"name":"Hunter Goodman","form_pct":44,"form_arrow":"down","pb":10.3,"hh":60.8,"la":22.9,"zone":0.088,"test":94.323},{"name":"Kyle Karros","form_pct":77,"form_arrow":"up","pb":3.5,"hh":57.4,"la":19.9,"zone":0.119,"test":59.845},{"name":"Edouard Julien","form_pct":45,"form_arrow":"down","pb":3.6,"hh":44.4,"la":5.6,"zone":0.078,"test":45.662},{"name":"Jake McCarthy","form_pct":76,"form_arrow":"up","pb":2,"hh":27.8,"la":12.3,"zone":0.095,"test":33.543},{"name":"Troy Johnston","form_pct":45,"form_arrow":"up","pb":1.7,"hh":47.5,"la":18.2,"zone":0.106,"test":32.436},{"name":"TJ Rumfield","form_pct":45,"form_arrow":"up","pb":0,"hh":17.5,"la":18.5,"zone":0.076,"test":20.305},{"name":"Ezequiel Tovar","form_pct":47,"form_arrow":"down","pb":5.7,"hh":44.2,"la":21.2,"zone":0.146,"test":53.337},{"name":"Brett Sullivan","form_pct":58,"form_arrow":"down","pb":1.5,"hh":33.9,"la":16,"zone":0.03,"test":24.901},{"name":"Willi Castro","form_pct":57,"form_arrow":"flat","pb":3.6,"hh":42.4,"la":16.9,"zone":0.127,"test":35.134},{"name":"Cole Carrigg","form_pct":51,"form_arrow":"up","pb":4.2,"hh":50,"la":17,"zone":0.055,"test":40.532},{"name":"Mickey Moniak","form_pct":60,"form_arrow":"flat","pb":6,"hh":27.8,"la":15.7,"zone":0.048,"test":30.211}],"LAD":[{"name":"Shohei Ohtani","form_pct":37,"form_arrow":"down","pb":14.4,"hh":67,"la":18,"zone":0.082,"test":98.783},{"name":"Max Muncy","form_pct":50,"form_arrow":"up","pb":10.3,"hh":55.5,"la":21.4,"zone":0.112,"test":78.058},{"name":"Mookie Betts","form_pct":58,"form_arrow":"up","pb":5.4,"hh":44.4,"la":21.3,"zone":0.04,"test":59.999},{"name":"Kyle Tucker","form_pct":70,"form_arrow":"up","pb":8.1,"hh":49.6,"la":19.7,"zone":0.082,"test":64.894},{"name":"Freddie Freeman","form_pct":57,"form_arrow":"flat","pb":6.6,"hh":53.4,"la":18.4,"zone":0.105,"test":62.288},{"name":"Alex Call","form_pct":37,"form_arrow":"down","pb":2.4,"hh":28.1,"la":19.4,"zone":0.061,"test":39.163},{"name":"Andy Pages","form_pct":44,"form_arrow":"up","pb":6.5,"hh":45,"la":20.6,"zone":0.069,"test":50.741},{"name":"Tommy Edman","form_pct":44,"form_arrow":"down","pb":2.9,"hh":39.1,"la":14.2,"zone":0.085,"test":34.222},{"name":"Alex Freeland","form_pct":34,"form_arrow":"down","pb":3.7,"hh":50.3,"la":14.8,"zone":0.093,"test":38.862},{"name":"Miguel Rojas","form_pct":61,"form_arrow":"up","pb":1.5,"hh":32.4,"la":13.3,"zone":0.051,"test":26.787},{"name":"Eliezer Alfonzo","form_pct":50,"form_arrow":"flat","pb":0,"hh":19.5,"la":15.3,"zone":0.01,"test":15.924},{"name":"Dalton Rushing","form_pct":56,"form_arrow":"up","pb":9.1,"hh":53.7,"la":16.9,"zone":0.075,"test":51.776},{"name":"Teoscar Hernández","form_pct":55,"form_arrow":"up","pb":6.9,"hh":51.2,"la":16,"zone":0.038,"test":36.423}]}}
